main.py
setup.py
currencyconverterapi/__init__.py
currencyconverterapi/client.py
currencyconverterapi/models.py
currecyconverterapi-1.0.1.dist-info/LICENSE
currecyconverterapi-1.0.1.dist-info/METADATA
currecyconverterapi-1.0.1.dist-info/WHEEL
currecyconverterapi-1.0.1.dist-info/entry_points.txt
currecyconverterapi-1.0.1.dist-info/top_level.txt
currecyconverterapi-1.0.1.dist-info/RECORD
