Metadata-Version: 2.1
Name: currecyconverterapi
Version: 1.0.1
Summary: Simplest currency converter with CurrecnyConverterApi
Home-page: https://github.com/yedhrab/currencyconverterapi
Author: Yunus Emre Ak
Author-email: yemreak.com@gmail.com
License: Apache Software License 2.0
Project-URL: Changelog, https://github.com/yedhrab/currecyconverterapi/blob/master/CHANGELOG.md
Project-URL: Issue Tracker, https://github.com/yedhrab/currecyconverterapi/issues
Keywords: currencyconverter,conveter,currecies
Platform: UNKNOWN
Classifier: Development Status :: 5 - Production/Stable
Classifier: Intended Audience :: Developers
Classifier: License :: OSI Approved :: BSD License
Classifier: Operating System :: Unix
Classifier: Operating System :: POSIX
Classifier: Operating System :: Microsoft :: Windows
Classifier: Programming Language :: Python
Classifier: Programming Language :: Python :: 2.7
Classifier: Programming Language :: Python :: 3
Classifier: Programming Language :: Python :: 3.5
Classifier: Programming Language :: Python :: 3.6
Classifier: Programming Language :: Python :: 3.7
Classifier: Programming Language :: Python :: 3.8
Classifier: Programming Language :: Python :: 3.9
Classifier: Programming Language :: Python :: 3.10
Classifier: Programming Language :: Python :: Implementation :: CPython
Classifier: Programming Language :: Python :: Implementation :: PyPy
Classifier: Topic :: Utilities
Requires-Python: >=2.7, !=3.0.*, !=3.1.*, !=3.2.*, !=3.3.*, !=3.4.*
License-File: LICENSE
Requires-Dist: ruamel.yaml (==0.17.21)
